[
  {
    "title": "Fauci: \u2018Bizarre\u2019 White House Behavior Only Hurts the President",
    "url": "https://www.theatlantic.com/politics/archive/2020/07/trump-fauci-coronavirus-pandemic-oppo/614224/",
    "source": "The Atlantic",
    "time": "20 hours ago",
    "date": "2020-07-16 10:00:00",
    "query": "Anthony Fauci",
    "story_position": 1,
    "domain": "www.theatlantic.com"
  },
  {
    "title": "Fact check: Peter Navarro's claims about Dr. Anthony Fauci are misleading, \nlack context",
    "url": "https://www.usatoday.com/story/news/politics/2020/07/15/fact-check-trump-adviser-navarro-claims-fauci-misleading/5443826002/",
    "source": "USATODAY.com",
    "time": "15 hours ago",
    "date": "2020-07-16 10:00:00",
    "query": "Anthony Fauci",
    "story_position": 2,
    "domain": "www.usatoday.com"
  },
  {
    "title": "Dr. Anthony Fauci is the Galileo of the coronavirus pandemic",
    "url": "https://www.azcentral.com/story/opinion/op-ed/ej-montini/2020/07/16/anthony-fauci-galileo-coronavirus-pandemic/5449212002/",
    "source": "The Arizona Republic",
    "time": "15 mins ago",
    "date": "2020-07-16 10:00:00",
    "query": "Anthony Fauci",
    "story_position": 3,
    "domain": "www.azcentral.com"
  },
  {
    "title": "'I think I'm pretty effective:' Fauci says he's staying in his job despite \n'complicated' relationship with Trump",
    "url": "https://www.usatoday.com/story/news/politics/2020/07/16/anthony-fauci-says-he-has-complicated-relationship-trump/5449906002/",
    "source": "USATODAY.com",
    "time": "20 mins ago",
    "date": "2020-07-16 10:00:00",
    "query": "Anthony Fauci",
    "story_position": 4,
    "domain": "www.usatoday.com"
  },
  {
    "title": "Trump administration retreats from war with Anthony Fauci - Business Insider",
    "url": "https://www.businessinsider.com/trump-administration-retreats-from-war-with-anthony-fauci-2020-7",
    "source": "Business Insider",
    "time": "1 hour ago",
    "date": "2020-07-16 10:00:00",
    "query": "Anthony Fauci",
    "story_position": 5,
    "domain": "www.businessinsider.com"
  },
  {
    "title": "Trump's coronavirus team puts internal battles on public display",
    "url": "https://www.nbcnews.com/politics/white-house/trump-s-coronavirus-team-puts-internal-battles-public-display-n1234011",
    "source": "NBC News",
    "time": "1 hour ago",
    "date": "2020-07-16 10:00:00",
    "query": "Anthony Fauci",
    "story_position": 6,
    "domain": "www.nbcnews.com"
  },
  {
    "title": "The smartest political advice from the least political person",
    "url": "https://www.washingtonpost.com/opinions/2020/07/16/smartest-political-advice-least-political-person/",
    "source": "Washington Post",
    "time": "2 hours ago",
    "date": "2020-07-16 10:00:00",
    "query": "Anthony Fauci",
    "story_position": 7,
    "domain": "www.washingtonpost.com"
  },
  {
    "title": "Dr. Anthony Fauci ditches the mask for magazine photo shoot",
    "url": "https://www.today.com/popculture/dr-fauci-ditches-mask-magazine-photoshoot-t186965",
    "source": "Today Show",
    "time": "9 hours ago",
    "date": "2020-07-16 10:00:00",
    "query": "Anthony Fauci",
    "story_position": 8,
    "domain": "www.today.com"
  },
  {
    "title": "New poll reaffirms that most Americans don't trust the president, but they \ndo trust Dr. Fauci",
    "url": "https://www.cnn.com/2020/07/15/media/poll-trump-fauci-reliable-sources/index.html",
    "source": "CNN.com",
    "time": "11 hours ago",
    "date": "2020-07-16 10:00:00",
    "query": "Anthony Fauci",
    "story_position": 9,
    "domain": "www.cnn.com"
  },
  {
    "title": "Tapper: Attacks on Fauci the ultimate in irresponsibility",
    "url": "https://www.cnn.com/videos/politics/2020/07/15/jake-tapper-fauci-attacks-disgusting-lead-sot-vpx.cnn",
    "source": "CNN.com",
    "time": "15 hours ago",
    "date": "2020-07-16 10:00:00",
    "query": "Anthony Fauci",
    "story_position": 10,
    "domain": "www.cnn.com"
  }
]