[
  {
    "title": "Trump presses attack on Fauci in dispute over campaign ad",
    "url": "https://news.yahoo.com/anthony-fauci-president-trump-campaign-ad-coronavirus-141237571.html",
    "source": "Yahoo News",
    "time": "1 day ago",
    "date": "2020-10-14 22:00:00",
    "query": "Anthony Fauci",
    "story_position": 1,
    "domain": "news.yahoo.com"
  },
  {
    "title": "Dr. Fauci says his kids aren't coming home for Thanksgiving as Americans \n'sacrifice' holiday gatherings to stay safe from coronavirus",
    "url": "https://www.cnbc.com/2020/10/14/dr-fauci-says-his-kids-arent-coming-home-for-thanksgiving-to-stay-safe-from-coronavirus.html",
    "source": "CNBC",
    "time": "5 hours ago",
    "date": "2020-10-14 22:00:00",
    "query": "Anthony Fauci",
    "story_position": 2,
    "domain": "www.cnbc.com"
  },
  {
    "title": "Live: Dr. Anthony Fauci joins Yahoo News to discuss the coronavirus pandemic",
    "url": "https://news.yahoo.com/live-fauci-yahoo-news-interview-173247615.html",
    "source": "Yahoo News",
    "time": "8 hours ago",
    "date": "2020-10-14 22:00:00",
    "query": "Anthony Fauci",
    "story_position": 3,
    "domain": "news.yahoo.com"
  },
  {
    "title": "As 2020 campaign enters home stretch, Fauci pulled into fray",
    "url": "https://news.yahoo.com/2020-campaign-enters-home-stretch-015007195.html",
    "source": "Yahoo! Voices",
    "time": "20 mins ago",
    "date": "2020-10-14 22:00:00",
    "query": "Anthony Fauci",
    "story_position": 4,
    "domain": "news.yahoo.com"
  },
  {
    "title": "Dr. Fauci on COVID surge, Trump's recovery, holiday travel and more - Full \ninterview",
    "url": "https://www.cbsnews.com/video/dr-fauci-on-covid-surge-trumps-recovery-holiday-travel-and-more-full-interview/",
    "source": "CBS News",
    "time": "5 hours ago",
    "date": "2020-10-14 22:00:00",
    "query": "Anthony Fauci",
    "story_position": 5,
    "domain": "www.cbsnews.com"
  },
  {
    "title": "Fauci: Trump's rapid recovery 'amplifies' misunderstanding of Covid-19",
    "url": "https://www.statnews.com/2020/10/13/fauci-trumps-rapid-recovery-from-covid-19-while-welcome-amplifies-public-misunderstanding-of-disease/",
    "source": "STAT",
    "time": "1 day ago",
    "date": "2020-10-14 22:00:00",
    "query": "Anthony Fauci",
    "story_position": 6,
    "domain": "www.statnews.com"
  },
  {
    "title": "Fauci says he's 'not going to walk away' as Trump revives criticism",
    "url": "https://www.cnn.com/2020/10/13/politics/trump-versus-fauci/index.html",
    "source": "CNN",
    "time": "1 day ago",
    "date": "2020-10-14 22:00:00",
    "query": "Anthony Fauci",
    "story_position": 7,
    "domain": "www.cnn.com"
  },
  {
    "title": "Bill Gates defends Dr. Fauci, blasts the U.S. coronavirus response as \n'among the worst of any country'",
    "url": "https://www.marketwatch.com/story/bill-gates-defends-dr-fauci-blasts-the-u-s-coronavirus-response-as-among-the-worst-of-any-country-11602701971",
    "source": "MarketWatch",
    "time": "7 hours ago",
    "date": "2020-10-14 22:00:00",
    "query": "Anthony Fauci",
    "story_position": 8,
    "domain": "www.marketwatch.com"
  },
  {
    "title": "Trump attacks Fauci with falsehoods after backlash for quoting him out of \ncontext in campaign ad",
    "url": "https://abcnews.go.com/Politics/trump-attacks-fauci-falsehoods-backlash-quoting-context-campaign/story?id=73583139",
    "source": "ABC News",
    "time": "1 day ago",
    "date": "2020-10-14 22:00:00",
    "query": "Anthony Fauci",
    "story_position": 9,
    "domain": "abcnews.go.com"
  },
  {
    "title": "Fauci has 'high degree of confidence' Trump no longer shedding coronavirus \n| TheHill",
    "url": "https://thehill.com/homenews/administration/521025-fauci-has-high-degree-of-confidence-trump-no-longer-shedding",
    "source": "The Hill",
    "time": "7 hours ago",
    "date": "2020-10-14 22:00:00",
    "query": "Anthony Fauci",
    "story_position": 10,
    "domain": "thehill.com"
  }
]