[
  {
    "title": "Fauci warns these 7 states are at risk for COVID-19 surge over Labor Day \nweekend",
    "url": "https://nypost.com/2020/09/04/fauci-warns-7-states-need-to-be-covid-19-cautious-over-labor-day-weekend/",
    "source": "New York Post",
    "time": "2 hours ago",
    "date": "2020-09-04 22:00:00",
    "query": "Anthony Fauci",
    "story_position": 1,
    "domain": "nypost.com"
  },
  {
    "title": "Tiffany Haddish Tells Dr. Anthony Fauci She Tested Positive For Coronavirus",
    "url": "https://deadline.com/2020/09/tiffany-haddish-tells-dr-anthony-fauci-she-tested-positive-for-coronavirus-1234571395/",
    "source": "Deadline",
    "time": "40 mins ago",
    "date": "2020-09-04 22:00:00",
    "query": "Anthony Fauci",
    "story_position": 2,
    "domain": "deadline.com"
  },
  {
    "title": "Fauci warns that Illinois and six other states are at higher risk for a \nCOVID-19 surge over Labor Day weekend,",
    "url": "https://www.chicagotribune.com/coronavirus/ct-fauci-illinois-coronavirus-labor-day-warning-20200904-f2fjnqtm7ngwjesb5ai4oizar4-story.html",
    "source": "Chicago Tribune",
    "time": "5 hours ago",
    "date": "2020-09-04 22:00:00",
    "query": "Anthony Fauci",
    "story_position": 3,
    "domain": "www.chicagotribune.com"
  },
  {
    "title": "Tiffany Haddish Reveals She Contracted COVID-19, Interviews Dr. Anthony \nFauci in New Video",
    "url": "https://variety.com/2020/film/news/tiffany-haddish-covid-19-dr-anthony-fauci-1234760389/",
    "source": "Variety",
    "time": "2 hours ago",
    "date": "2020-09-04 22:00:00",
    "query": "Anthony Fauci",
    "story_position": 4,
    "domain": "variety.com"
  },
  {
    "title": "Fauci shares warning for Missouri, Illinois ahead of Labor Day weekend",
    "url": "https://www.ksdk.com/article/news/health/coronavirus/fauci-coronavirus-surge-warning-missouri-illinois/63-bef89e25-9b0f-4e02-88f1-601f5ad4b56d",
    "source": "KSDK.com",
    "time": "8 hours ago",
    "date": "2020-09-04 22:00:00",
    "query": "Anthony Fauci",
    "story_position": 5,
    "domain": "www.ksdk.com"
  },
  {
    "title": "Fauci Warns Seven Midwest States to Be on Alert Over Labor Day",
    "url": "https://www.bloomberg.com/news/articles/2020-09-03/fauci-warns-seven-midwest-states-to-be-on-alert-over-labor-day",
    "source": "Bloomberg",
    "time": "1 day ago",
    "date": "2020-09-04 22:00:00",
    "query": "Anthony Fauci",
    "story_position": 6,
    "domain": "www.bloomberg.com"
  },
  {
    "title": "Fauci: Vaccine in October 'unlikely, not impossible'",
    "url": "https://www.cnn.com/videos/health/2020/09/03/coronavirus-wrap-vaccine-0903-watt-pkg-lead-vpx.cnn",
    "source": "CNN",
    "time": "1 day ago",
    "date": "2020-09-04 22:00:00",
    "query": "Anthony Fauci",
    "story_position": 7,
    "domain": "www.cnn.com"
  },
  {
    "title": "Fauci: Indiana one of seven states at risk of COVID-19 surge",
    "url": "https://wpta21.com/2020/09/04/fauci-indiana-one-of-seven-states-at-risk-of-covid-19-surge/",
    "source": "wpta21.com",
    "time": "12 hours ago",
    "date": "2020-09-04 22:00:00",
    "query": "Anthony Fauci",
    "story_position": 8,
    "domain": "wpta21.com"
  },
  {
    "title": "Dr. Fauci: This is the good news",
    "url": "https://www.cnn.com/videos/health/2020/09/03/dr-fauci-vaccine-newsroom-bts-vpx.cnn",
    "source": "CNN",
    "time": "1 day ago",
    "date": "2020-09-04 22:00:00",
    "query": "Anthony Fauci",
    "story_position": 9,
    "domain": "www.cnn.com"
  },
  {
    "title": "COVID-19 at colleges: Fauci warns not to send students home",
    "url": "https://www.nbcnews.com/health/health-news/covid-19-colleges-fauci-urges-schools-keep-students-campus-outbreaks-n1238997",
    "source": "NBC News",
    "time": "1 day ago",
    "date": "2020-09-04 22:00:00",
    "query": "Anthony Fauci",
    "story_position": 10,
    "domain": "www.nbcnews.com"
  }
]