[
  {
    "title": "Open letter to Dr. Anthony Fauci regarding the use of hydroxychloroquine \nfor treating COVID-19",
    "url": "https://www.thedesertreview.com/opinion/columnists/open-letter-to-dr-anthony-fauci-regarding-the-use-of-hydroxychloroquine-for-treating-covid-19/article_31d37842-dd8f-11ea-80b5-bf80983bc072.html",
    "source": "thedesertreview.com",
    "time": "1 week ago",
    "date": "2020-08-23 22:00:00",
    "query": "Anthony Fauci",
    "story_position": 1,
    "domain": "www.thedesertreview.com"
  },
  {
    "title": "Q&A with Dr. Fauci: \u2018We will get out of this and we will return to normal. \nDon\u2019t despair.\u2019",
    "url": "https://www.washingtonpost.com/entertainment/qanda-with-dr-fauci-we-will-get-out-of-this-and-we-will-return-to-normal-dont-despair/2020/08/20/e986cca8-e232-11ea-b69b-64f7b0477ed4_story.html",
    "source": "Washington Post",
    "time": "2 days ago",
    "date": "2020-08-23 22:00:00",
    "query": "Anthony Fauci",
    "story_position": 2,
    "domain": "www.washingtonpost.com"
  },
  {
    "title": "What causes vocal polyps, the condition Fauci had surgery for - Insider",
    "url": "https://www.insider.com/what-are-vocal-polyps-anthony-fauci-surgery-2020-8",
    "source": "INSIDER",
    "time": "3 days ago",
    "date": "2020-08-23 22:00:00",
    "query": "Anthony Fauci",
    "story_position": 3,
    "domain": "www.insider.com"
  }
]