[
  {
    "title": "Fauci warns these 7 states are at risk for COVID-19 surge over Labor Day \nweekend",
    "url": "https://nypost.com/2020/09/04/fauci-warns-7-states-need-to-be-covid-19-cautious-over-labor-day-weekend/",
    "source": "New York Post",
    "time": "2 days ago",
    "date": "2020-09-06 22:00:00",
    "query": "Anthony Fauci",
    "story_position": 1,
    "domain": "nypost.com"
  },
  {
    "title": "Fauci warns that Illinois and six other states are at higher risk for a \nCOVID-19 surge over Labor Day weekend,",
    "url": "https://www.chicagotribune.com/coronavirus/ct-fauci-illinois-coronavirus-labor-day-warning-20200904-f2fjnqtm7ngwjesb5ai4oizar4-story.html",
    "source": "Chicago Tribune",
    "time": "2 days ago",
    "date": "2020-09-06 22:00:00",
    "query": "Anthony Fauci",
    "story_position": 2,
    "domain": "www.chicagotribune.com"
  },
  {
    "title": "Anthony Fauci says sending students home is 'the worst thing you could do'",
    "url": "https://www.collegian.psu.edu/news/national/article_9552e9cc-efd5-11ea-90af-ffc2a6898888.html",
    "source": "The Daily Collegian Online",
    "time": "1 day ago",
    "date": "2020-09-06 22:00:00",
    "query": "Anthony Fauci",
    "story_position": 3,
    "domain": "www.collegian.psu.edu"
  }
]