[
  {
    "title": "Fauci warns of 'more ominous' strains of COVID-19 from Brazil, South Africa",
    "url": "https://nypost.com/2021/01/17/fauci-warns-more-ominous-strains-of-covid-19-have-emerged/",
    "source": "New York Post",
    "time": "23 hours ago",
    "date": "2021-01-18 10:00:00",
    "query": "Anthony Fauci",
    "story_position": 1,
    "domain": "nypost.com"
  },
  {
    "title": "Fauci says 2 new vaccines could be ready for US approval within weeks, not \nmonths - Business Insider",
    "url": "https://www.businessinsider.com/fauci-covid-vaccine-fda-approval-johnson-johnson-astrazeneca-2021-1",
    "source": "Business Insider",
    "time": "3 hours ago",
    "date": "2021-01-18 10:00:00",
    "query": "Anthony Fauci",
    "story_position": 2,
    "domain": "www.businessinsider.com"
  },
  {
    "title": "Biden plan to vaccinate 100m people in 100 days \u2018absolutely doable\u2019, Fauci \nsays",
    "url": "https://www.theguardian.com/world/2021/jan/17/joe-biden-covid-vaccination-plan-fauci",
    "source": "The Guardian",
    "time": "21 hours ago",
    "date": "2021-01-18 10:00:00",
    "query": "Anthony Fauci",
    "story_position": 3,
    "domain": "www.theguardian.com"
  },
  {
    "title": "Fauci says Biden goal of 100 million doses in 100 days 'can be done'",
    "url": "https://news.yahoo.com/fauci-says-biden-goal-100-202244100.html",
    "source": "Yahoo News",
    "time": "18 hours ago",
    "date": "2021-01-18 10:00:00",
    "query": "Anthony Fauci",
    "story_position": 4,
    "domain": "news.yahoo.com"
  },
  {
    "title": "Fauci: New COVID-19 vaccines could be \u2018weeks away\u2019 from possible approval",
    "url": "https://www.foxbusiness.com/lifestyle/fauci-new-covid-19-vaccines-could-be-weeks-away-from-possible-approval",
    "source": "Fox Business",
    "time": "18 hours ago",
    "date": "2021-01-18 10:00:00",
    "query": "Anthony Fauci",
    "story_position": 5,
    "domain": "www.foxbusiness.com"
  },
  {
    "title": "Fauci says new vaccines could be ready for possible approval within weeks, \nnot months",
    "url": "https://www.nbcnews.com/politics/meet-the-press/fauci-weeks-not-months-new-vaccines-are-submitted-approval-n1254543",
    "source": "NBC News",
    "time": "23 hours ago",
    "date": "2021-01-18 10:00:00",
    "query": "Anthony Fauci",
    "story_position": 6,
    "domain": "www.nbcnews.com"
  },
  {
    "title": "Boston woman in her 20s confirmed as first case of coronavirus variant in \nMassachusetts",
    "url": "https://www.bostonherald.com/2021/01/17/dr-anthony-fauci-says-federal-approval-of-johnson-johnson-astrazeneca-vaccines-is-weeks-away/",
    "source": "Boston Herald",
    "time": "16 hours ago",
    "date": "2021-01-18 10:00:00",
    "query": "Anthony Fauci",
    "story_position": 7,
    "domain": "www.bostonherald.com"
  },
  {
    "title": "Fauci: Approval of AstraZeneca and Johnson & Johnson vaccines likely 'weeks \naway' | TheHill",
    "url": "https://thehill.com/homenews/sunday-talk-shows/534620-fauci-approval-of-astrazeneca-and-jj-vaccines-likely-weeks-away",
    "source": "The Hill",
    "time": "23 hours ago",
    "date": "2021-01-18 10:00:00",
    "query": "Anthony Fauci",
    "story_position": 8,
    "domain": "thehill.com"
  },
  {
    "title": "Fauci Says Biden\u2019s 100 Million Vaccine Goal \u2018Absolutely Doable\u2019",
    "url": "https://www.bloomberg.com/news/articles/2021-01-17/fauci-says-biden-s-100-million-doses-doable-in-100-days",
    "source": "Bloomberg",
    "time": "23 hours ago",
    "date": "2021-01-18 10:00:00",
    "query": "Anthony Fauci",
    "story_position": 9,
    "domain": "www.bloomberg.com"
  },
  {
    "title": "Federal approval of Johnson & Johnson, AstraZeneca vaccines is \u2018weeks \naway:\u2019 Dr. Anthony Fauci",
    "url": "https://www.nydailynews.com/coronavirus/ny-covid-anthony-fauci-joe-biden-vaccination-20210117-2fxxwgcd6zhnlpfuzonuv3d65i-story.html",
    "source": "New York Daily News",
    "time": "22 hours ago",
    "date": "2021-01-18 10:00:00",
    "query": "Anthony Fauci",
    "story_position": 10,
    "domain": "www.nydailynews.com"
  }
]