[
  {
    "title": "Fauci looking ahead to more vaccines in March, April",
    "url": "https://www.politico.com/news/2021/02/07/fauci-vaccines-march-april-466776",
    "source": "Politico",
    "time": "9 hours ago",
    "date": "2021-02-07 22:00:00",
    "query": "Anthony Fauci",
    "story_position": 1,
    "domain": "www.politico.com"
  },
  {
    "title": "Fauci says the US should prioritize second vaccine doses - Business Insider",
    "url": "https://www.businessinsider.com/fauci-us-should-prioritize-second-vaccine-doses-2021-2",
    "source": "Business Insider",
    "time": "9 hours ago",
    "date": "2021-02-07 22:00:00",
    "query": "Anthony Fauci",
    "story_position": 2,
    "domain": "www.businessinsider.com"
  },
  {
    "title": "Fauci says U.S. vaccinations to increase in spring as Biden administration \nnears doses goal",
    "url": "https://www.washingtonpost.com/health/2021/02/07/fauci-vaccination-increase/",
    "source": "Washington Post",
    "time": "3 hours ago",
    "date": "2021-02-07 22:00:00",
    "query": "Anthony Fauci",
    "story_position": 3,
    "domain": "www.washingtonpost.com"
  }
]