[
  {
    "title": "Presidential debate: Trump lies about Fauci's coronavirus advice in heated \nexchange",
    "url": "https://www.independent.co.uk/news/world/americas/us-election-2020/presidential-debate-trump-fauci-covid-fact-check-biden-b1239264.html",
    "source": "The Independent",
    "time": "11 hours ago",
    "date": "2020-10-23 10:00:00",
    "query": "Anthony Fauci",
    "story_position": 1,
    "domain": "www.independent.co.uk"
  },
  {
    "title": "A 'building distrust' in public health agencies is 'the elephant in the \nroom,' Fauci says",
    "url": "https://www.cnn.com/2020/10/22/health/fauci-distrust-building-coronavirus/index.html",
    "source": "CNN",
    "time": "1 day ago",
    "date": "2020-10-23 10:00:00",
    "query": "Anthony Fauci",
    "story_position": 2,
    "domain": "www.cnn.com"
  },
  {
    "title": "How Trump success in ending Obamacare would kill Fauci plan to conquer HIV",
    "url": "https://www.theguardian.com/society/2020/oct/23/trump-obamacare-aca-fauci-plan-hiv-supreme-court-amy-coney-barrett",
    "source": "The Guardian",
    "time": "15 mins ago",
    "date": "2020-10-23 10:00:00",
    "query": "Anthony Fauci",
    "story_position": 3,
    "domain": "www.theguardian.com"
  },
  {
    "title": "Trump Debates Himself on Dr. Anthony Fauci",
    "url": "https://www.thedailybeast.com/donald-trump-debates-himself-on-anthony-fauci",
    "source": "Daily Beast",
    "time": "12 hours ago",
    "date": "2020-10-23 10:00:00",
    "query": "Anthony Fauci",
    "story_position": 4,
    "domain": "www.thedailybeast.com"
  },
  {
    "title": "Fauci: Masks, Social Distancing Likely Until 2022",
    "url": "https://www.webmd.com/lung/news/20201022/fauci-masks-social-distancing-likely-until-2022",
    "source": "WebMD",
    "time": "20 hours ago",
    "date": "2020-10-23 10:00:00",
    "query": "Anthony Fauci",
    "story_position": 5,
    "domain": "www.webmd.com"
  },
  {
    "title": "Fauci\u2019s refusal to quit shouldn\u2019t surprise anyone",
    "url": "https://www.washingtonpost.com/opinions/faucis-refusal-to-quit-shouldnt-surprise-anyone/2020/10/20/974d2188-130d-11eb-ad6f-36c93e6e94fb_story.html",
    "source": "Washington Post",
    "time": "2 days ago",
    "date": "2020-10-23 10:00:00",
    "query": "Anthony Fauci",
    "story_position": 6,
    "domain": "www.washingtonpost.com"
  },
  {
    "title": "Republican senators defend Fauci as Trump escalates attacks",
    "url": "https://www.axios.com/republican-senators-defend-fauci-as-trump-escalates-attacks-10f0c34b-417d-41aa-bdfe-db4fa0c33059.html",
    "source": "Axios",
    "time": "2 days ago",
    "date": "2020-10-23 10:00:00",
    "query": "Anthony Fauci",
    "story_position": 7,
    "domain": "www.axios.com"
  },
  {
    "title": "The facts behind Trump's attacks on Fauci",
    "url": "https://news.yahoo.com/the-facts-behind-trumps-attacks-on-fauci-174107315.html",
    "source": "Yahoo News",
    "time": "2 days ago",
    "date": "2020-10-23 10:00:00",
    "query": "Anthony Fauci",
    "story_position": 8,
    "domain": "news.yahoo.com"
  },
  {
    "title": "Fauci quotes 'The Godfather' in response to Trump criticisms",
    "url": "https://nypost.com/2020/10/20/fauci-responds-to-trump-criticisms-with-the-godfather-quote-report/",
    "source": "New York Post",
    "time": "3 days ago",
    "date": "2020-10-23 10:00:00",
    "query": "Anthony Fauci",
    "story_position": 9,
    "domain": "nypost.com"
  },
  {
    "title": "Should You Cancel Thanksgiving? What Fauci and Other Experts Say About \nCelebrating During COVID",
    "url": "https://www.newsweek.com/cancel-thanksgiving-fauci-experts-covid-1540249",
    "source": "Newsweek",
    "time": "1 day ago",
    "date": "2020-10-23 10:00:00",
    "query": "Anthony Fauci",
    "story_position": 10,
    "domain": "www.newsweek.com"
  }
]